windows_hotkey_checker/__init__.py
windows_hotkey_checker/__main__.py
windows_hotkey_checker/hotkeys.py
windows_hotkey_checker-0.1.11.dist-info/LICENSE
windows_hotkey_checker-0.1.11.dist-info/METADATA
windows_hotkey_checker-0.1.11.dist-info/WHEEL
windows_hotkey_checker-0.1.11.dist-info/entry_points.txt
windows_hotkey_checker-0.1.11.dist-info/top_level.txt
windows_hotkey_checker-0.1.11.dist-info/RECORD
