Metadata-Version: 2.1
Name: windows-hotkey-checker
Version: 0.1.11
Summary: A simple command line tool to check whether a hotkey is already registered by another program on Windows.
Project-URL: Repository, https://github.com/heathhenley/windows_hotkey_checker
Classifier: Environment :: Console
Classifier: Intended Audience :: Developers
Classifier: License :: OSI Approved :: MIT License
Classifier: Operating System :: Microsoft :: Windows
Classifier: Programming Language :: Python :: 3
Classifier: Topic :: Software Development :: Libraries :: Python Modules
Classifier: Topic :: Utilities
Requires-Python: >=3.10
License-File: LICENSE
Requires-Dist: pytest (>=7.2.2)
Requires-Dist: pytest-mock (>=3.10.0)
Requires-Dist: pywin32-ctypes (>=0.2.0)
